{"level":"info","msg":"\nTransferred:   \t          0 B / 2 GiB, 0%, 0 B/s, ETA -\nTransferred:            0 / 5, 0%\nElapsed time:        10.2s\nTransferring:\n *                                testfile_02G_3: transferring\n *                                testfile_02G_1: transferring\n *                                testfile_02G_4: transferring\n *                                testfile_02G_2: transferring\n\n","source":"accounting/stats.go:526","stats":{"bytes":0,"checks":0,"deletedDirs":0,"deletes":0,"elapsedTime":10.246808249,"errors":0,"eta":null,"fatalError":false,"renames":0,"retryError":false,"serverSideCopies":0,"serverSideCopyBytes":0,"serverSideMoveBytes":0,"serverSideMoves":0,"speed":0,"totalBytes":2147483648,"totalChecks":0,"totalTransfers":5,"transferTime":9.926276856,"transferring":[{"dstFs":"e2-s3perf-20240501-sg:e2-s3perf-20240501-sg/02000m","name":"testfile_02G_3","size":2147483648,"srcFs":"/mnt/blockstorage/02000m"},{"dstFs":"e2-s3perf-20240501-sg:e2-s3perf-20240501-sg/02000m","name":"testfile_02G_1","size":2147483648,"srcFs":"/mnt/blockstorage/02000m"},{"dstFs":"e2-s3perf-20240501-sg:e2-s3perf-20240501-sg/02000m","name":"testfile_02G_4","size":2147483648,"srcFs":"/mnt/blockstorage/02000m"},{"dstFs":"e2-s3perf-20240501-sg:e2-s3perf-20240501-sg/02000m","name":"testfile_02G_2","size":2147483648,"srcFs":"/mnt/blockstorage/02000m"}],"transfers":0},"time":"2024-05-03T14:56:35.248117+00:00"}
{"level":"info","msg":"\nTransferred:   \t          0 B / 2 GiB, 0%, 0 B/s, ETA -\nTransferred:            0 / 5, 0%\nElapsed time:        20.2s\nTransferring:\n *                                testfile_02G_3: transferring\n *                                testfile_02G_1: transferring\n *                                testfile_02G_4: transferring\n *                                testfile_02G_2: transferring\n\n","source":"accounting/stats.go:526","stats":{"bytes":0,"checks":0,"deletedDirs":0,"deletes":0,"elapsedTime":20.246798543,"errors":0,"eta":null,"fatalError":false,"renames":0,"retryError":false,"serverSideCopies":0,"serverSideCopyBytes":0,"serverSideMoveBytes":0,"serverSideMoves":0,"speed":0,"totalBytes":2147483648,"totalChecks":0,"totalTransfers":5,"transferTime":19.926291756,"transferring":[{"dstFs":"e2-s3perf-20240501-sg:e2-s3perf-20240501-sg/02000m","name":"testfile_02G_3","size":2147483648,"srcFs":"/mnt/blockstorage/02000m"},{"dstFs":"e2-s3perf-20240501-sg:e2-s3perf-20240501-sg/02000m","name":"testfile_02G_1","size":2147483648,"srcFs":"/mnt/blockstorage/02000m"},{"dstFs":"e2-s3perf-20240501-sg:e2-s3perf-20240501-sg/02000m","name":"testfile_02G_4","size":2147483648,"srcFs":"/mnt/blockstorage/02000m"},{"dstFs":"e2-s3perf-20240501-sg:e2-s3perf-20240501-sg/02000m","name":"testfile_02G_2","size":2147483648,"srcFs":"/mnt/blockstorage/02000m"}],"transfers":0},"time":"2024-05-03T14:56:45.247761+00:00"}
{"level":"info","msg":"\nTransferred:   \t          0 B / 2 GiB, 0%, 0 B/s, ETA -\nTransferred:            0 / 5, 0%\nElapsed time:        30.2s\nTransferring:\n *                                testfile_02G_3: transferring\n *                                testfile_02G_1: transferring\n *                                testfile_02G_4: transferring\n *                                testfile_02G_2: transferring\n\n","source":"accounting/stats.go:526","stats":{"bytes":0,"checks":0,"deletedDirs":0,"deletes":0,"elapsedTime":30.24660432,"errors":0,"eta":null,"fatalError":false,"renames":0,"retryError":false,"serverSideCopies":0,"serverSideCopyBytes":0,"serverSideMoveBytes":0,"serverSideMoves":0,"speed":0,"totalBytes":2147483648,"totalChecks":0,"totalTransfers":5,"transferTime":29.926098675,"transferring":[{"dstFs":"e2-s3perf-20240501-sg:e2-s3perf-20240501-sg/02000m","name":"testfile_02G_3","size":2147483648,"srcFs":"/mnt/blockstorage/02000m"},{"dstFs":"e2-s3perf-20240501-sg:e2-s3perf-20240501-sg/02000m","name":"testfile_02G_1","size":2147483648,"srcFs":"/mnt/blockstorage/02000m"},{"dstFs":"e2-s3perf-20240501-sg:e2-s3perf-20240501-sg/02000m","name":"testfile_02G_4","size":2147483648,"srcFs":"/mnt/blockstorage/02000m"},{"dstFs":"e2-s3perf-20240501-sg:e2-s3perf-20240501-sg/02000m","name":"testfile_02G_2","size":2147483648,"srcFs":"/mnt/blockstorage/02000m"}],"transfers":0},"time":"2024-05-03T14:56:55.247543+00:00"}
{"level":"info","msg":"\nTransferred:   \t  677.250 MiB / 10 GiB, 7%, 31.221 MiB/s, ETA 5m6s\nTransferred:            0 / 5, 0%\nElapsed time:        40.2s\nTransferring:\n *                                testfile_02G_3:  9% /2Gi, 22.494Mi/s, 1m22s\n *                                testfile_02G_1:  5% /2Gi, 13.764Mi/s, 2m20s\n *                                testfile_02G_4:  8% /2Gi, 20.392Mi/s, 1m31s\n *                                testfile_02G_2:  9% /2Gi, 21.082Mi/s, 1m28s\n\n","source":"accounting/stats.go:526","stats":{"bytes":710148096,"checks":0,"deletedDirs":0,"deletes":0,"elapsedTime":40.246617054,"errors":0,"eta":306,"fatalError":false,"renames":0,"retryError":false,"serverSideCopies":0,"serverSideCopyBytes":0,"serverSideMoveBytes":0,"serverSideMoves":0,"speed":32737935.247464705,"totalBytes":10737418240,"totalChecks":0,"totalTransfers":5,"transferTime":39.926118192,"transferring":[{"bytes":209715200,"dstFs":"e2-s3perf-20240501-sg:e2-s3perf-20240501-sg/02000m","eta":82,"group":"global_stats","name":"testfile_02G_3","percentage":9,"size":2147483648,"speed":26550938.892097875,"speedAvg":23586948.4510005,"srcFs":"/mnt/blockstorage/02000m"},{"bytes":115376128,"dstFs":"e2-s3perf-20240501-sg:e2-s3perf-20240501-sg/02000m","eta":140,"group":"global_stats","name":"testfile_02G_1","percentage":5,"size":2147483648,"speed":13815142.296487313,"speedAvg":14432178.591240559,"srcFs":"/mnt/blockstorage/02000m"},{"bytes":183500800,"dstFs":"e2-s3perf-20240501-sg:e2-s3perf-20240501-sg/02000m","eta":91,"group":"global_stats","name":"testfile_02G_4","percentage":8,"size":2147483648,"speed":23354851.9194049,"speedAvg":21382774.04682901,"srcFs":"/mnt/blockstorage/02000m"},{"bytes":201555968,"dstFs":"e2-s3perf-20240501-sg:e2-s3perf-20240501-sg/02000m","eta":88,"group":"global_stats","name":"testfile_02G_2","percentage":9,"size":2147483648,"speed":22924490.207079526,"speedAvg":22105702.35575875,"srcFs":"/mnt/blockstorage/02000m"}],"transfers":0},"time":"2024-05-03T14:57:05.247619+00:00"}
{"level":"info","msg":"\nTransferred:   \t    1.491 GiB / 10 GiB, 15%, 57.028 MiB/s, ETA 2m32s\nTransferred:            0 / 5, 0%\nElapsed time:        50.2s\nTransferring:\n *                                testfile_02G_3: 21% /2Gi, 23.797Mi/s, 1m7s\n *                                testfile_02G_1: 12% /2Gi, 13.569Mi/s, 2m12s\n *                                testfile_02G_4: 21% /2Gi, 24.408Mi/s, 1m5s\n *                                testfile_02G_2: 18% /2Gi, 20.119Mi/s, 1m22s\n\n","source":"accounting/stats.go:526","stats":{"bytes":1600978944,"checks":0,"deletedDirs":0,"deletes":0,"elapsedTime":50.258420053,"errors":0,"eta":152,"fatalError":false,"renames":0,"retryError":false,"serverSideCopies":0,"serverSideCopyBytes":0,"serverSideMoveBytes":0,"serverSideMoves":0,"speed":59797878.24686752,"totalBytes":10737418240,"totalChecks":0,"totalTransfers":5,"transferTime":49.937804141,"transferring":[{"bytes":466616320,"dstFs":"e2-s3perf-20240501-sg:e2-s3perf-20240501-sg/02000m","eta":67,"group":"global_stats","name":"testfile_02G_3","percentage":21,"size":2147483648,"speed":26052701.535368536,"speedAvg":24953341.712119926,"srcFs":"/mnt/blockstorage/02000m"},{"bytes":267386880,"dstFs":"e2-s3perf-20240501-sg:e2-s3perf-20240501-sg/02000m","eta":132,"group":"global_stats","name":"testfile_02G_1","percentage":12,"size":2147483648,"speed":14560917.136404317,"speedAvg":14227848.428539943,"srcFs":"/mnt/blockstorage/02000m"},{"bytes":466780160,"dstFs":"e2-s3perf-20240501-sg:e2-s3perf-20240501-sg/02000m","eta":65,"group":"global_stats","name":"testfile_02G_4","percentage":21,"size":2147483648,"speed":26122356.83538074,"speedAvg":25593913.232440118,"srcFs":"/mnt/blockstorage/02000m"},{"bytes":400195584,"dstFs":"e2-s3perf-20240501-sg:e2-s3perf-20240501-sg/02000m","eta":82,"group":"global_stats","name":"testfile_02G_2","percentage":18,"size":2147483648,"speed":21282359.249347493,"speedAvg":21096299.40556697,"srcFs":"/mnt/blockstorage/02000m"}],"transfers":0},"time":"2024-05-03T14:57:15.260053+00:00"}
{"level":"info","msg":"\nTransferred:   \t    2.314 GiB / 10 GiB, 23%, 69.374 MiB/s, ETA 1m53s\nTransferred:            0 / 5, 0%\nElapsed time:       1m0.2s\nTransferring:\n *                                testfile_02G_3: 35% /2Gi, 25.394Mi/s, 52s\n *                                testfile_02G_1: 17% /2Gi, 12.534Mi/s, 2m14s\n *                                testfile_02G_4: 35% /2Gi, 25.555Mi/s, 51s\n *                                testfile_02G_2: 27% /2Gi, 18.723Mi/s, 1m19s\n\n","source":"accounting/stats.go:526","stats":{"bytes":2485125120,"checks":0,"deletedDirs":0,"deletes":0,"elapsedTime":60.250231288,"errors":0,"eta":113,"fatalError":false,"renames":0,"retryError":false,"serverSideCopies":0,"serverSideCopyBytes":0,"serverSideMoveBytes":0,"serverSideMoves":0,"speed":72744269.17430402,"totalBytes":10737418240,"totalChecks":0,"totalTransfers":5,"transferTime":59.929727087,"transferring":[{"bytes":754974720,"dstFs":"e2-s3perf-20240501-sg:e2-s3perf-20240501-sg/02000m","eta":52,"group":"global_stats","name":"testfile_02G_3","percentage":35,"size":2147483648,"speed":27057882.824071582,"speedAvg":26627813.63072435,"srcFs":"/mnt/blockstorage/02000m"},{"bytes":382730240,"dstFs":"e2-s3perf-20240501-sg:e2-s3perf-20240501-sg/02000m","eta":134,"group":"global_stats","name":"testfile_02G_1","percentage":17,"size":2147483648,"speed":13497788.283239817,"speedAvg":13142369.03830724,"srcFs":"/mnt/blockstorage/02000m"},{"bytes":760217600,"dstFs":"e2-s3perf-20240501-sg:e2-s3perf-20240501-sg/02000m","eta":51,"group":"global_stats","name":"testfile_02G_4","percentage":35,"size":2147483648,"speed":27286395.734610807,"speedAvg":26796151.70243339,"srcFs":"/mnt/blockstorage/02000m"},{"bytes":587202560,"dstFs":"e2-s3perf-20240501-sg:e2-s3perf-20240501-sg/02000m","eta":79,"group":"global_stats","name":"testfile_02G_2","percentage":27,"size":2147483648,"speed":20391968.189107265,"speedAvg":19632117.167234708,"srcFs":"/mnt/blockstorage/02000m"}],"transfers":0},"time":"2024-05-03T14:57:25.251277+00:00"}
{"level":"info","msg":"\nTransferred:   \t    3.151 GiB / 10 GiB, 32%, 78.863 MiB/s, ETA 1m28s\nTransferred:            0 / 5, 0%\nElapsed time:      1m10.2s\nTransferring:\n *                                testfile_02G_3: 49% /2Gi, 28.009Mi/s, 37s\n *                                testfile_02G_1: 21% /2Gi, 10.487Mi/s, 2m32s\n *                                testfile_02G_4: 49% /2Gi, 27.897Mi/s, 37s\n *                                testfile_02G_2: 37% /2Gi, 20.071Mi/s, 1m4s\n\n","source":"accounting/stats.go:526","stats":{"bytes":3382870016,"checks":0,"deletedDirs":0,"deletes":0,"elapsedTime":70.250262904,"errors":0,"eta":88,"fatalError":false,"renames":0,"retryError":false,"serverSideCopies":0,"serverSideCopyBytes":0,"serverSideMoveBytes":0,"serverSideMoves":0,"speed":82694115.9590416,"totalBytes":10737418240,"totalChecks":0,"totalTransfers":5,"transferTime":69.929632997,"transferring":[{"bytes":1057718272,"dstFs":"e2-s3perf-20240501-sg:e2-s3perf-20240501-sg/02000m","eta":37,"group":"global_stats","name":"testfile_02G_3","percentage":49,"size":2147483648,"speed":27906420.20524924,"speedAvg":29369401.617353607,"srcFs":"/mnt/blockstorage/02000m"},{"bytes":466616320,"dstFs":"e2-s3perf-20240501-sg:e2-s3perf-20240501-sg/02000m","eta":152,"group":"global_stats","name":"testfile_02G_1","percentage":21,"size":2147483648,"speed":12165669.855265051,"speedAvg":10995893.10829453,"srcFs":"/mnt/blockstorage/02000m"},{"bytes":1060601856,"dstFs":"e2-s3perf-20240501-sg:e2-s3perf-20240501-sg/02000m","eta":37,"group":"global_stats","name":"testfile_02G_4","percentage":49,"size":2147483648,"speed":28013168.7974043,"speedAvg":29252628.833147585,"srcFs":"/mnt/blockstorage/02000m"},{"bytes":797933568,"dstFs":"e2-s3perf-20240501-sg:e2-s3perf-20240501-sg/02000m","eta":64,"group":"global_stats","name":"testfile_02G_2","percentage":37,"size":2147483648,"speed":20567447.127681967,"speedAvg":21046350.336859096,"srcFs":"/mnt/blockstorage/02000m"}],"transfers":0},"time":"2024-05-03T14:57:35.251865+00:00"}
{"level":"info","msg":"\nTransferred:   \t    4.009 GiB / 10 GiB, 40%, 82.410 MiB/s, ETA 1m14s\nTransferred:            0 / 5, 0%\nElapsed time:      1m20.2s\nTransferring:\n *                                testfile_02G_3: 62% /2Gi, 27.450Mi/s, 27s\n *                                testfile_02G_1: 28% /2Gi, 11.855Mi/s, 2m3s\n *                                testfile_02G_4: 63% /2Gi, 28.329Mi/s, 26s\n *                                testfile_02G_2: 45% /2Gi, 18.442Mi/s, 1m0s\n\n","source":"accounting/stats.go:526","stats":{"bytes":4304371712,"checks":0,"deletedDirs":0,"deletes":0,"elapsedTime":80.246446954,"errors":0,"eta":74,"fatalError":false,"renames":0,"retryError":false,"serverSideCopies":0,"serverSideCopyBytes":0,"serverSideMoveBytes":0,"serverSideMoves":0,"speed":86412806.48147091,"totalBytes":10737418240,"totalChecks":0,"totalTransfers":5,"transferTime":79.925942962,"transferring":[{"bytes":1347420160,"dstFs":"e2-s3perf-20240501-sg:e2-s3perf-20240501-sg/02000m","eta":27,"group":"global_stats","name":"testfile_02G_3","percentage":62,"size":2147483648,"speed":28130780.380132552,"speedAvg":28783369.185297564,"srcFs":"/mnt/blockstorage/02000m"},{"bytes":608174080,"dstFs":"e2-s3perf-20240501-sg:e2-s3perf-20240501-sg/02000m","eta":123,"group":"global_stats","name":"testfile_02G_1","percentage":28,"size":2147483648,"speed":12578248.65248057,"speedAvg":12430836.428347614,"srcFs":"/mnt/blockstorage/02000m"},{"bytes":1373634560,"dstFs":"e2-s3perf-20240501-sg:e2-s3perf-20240501-sg/02000m","eta":26,"group":"global_stats","name":"testfile_02G_4","percentage":63,"size":2147483648,"speed":28702955.21832496,"speedAvg":29704616.330670673,"srcFs":"/mnt/blockstorage/02000m"},{"bytes":975175680,"dstFs":"e2-s3perf-20240501-sg:e2-s3perf-20240501-sg/02000m","eta":60,"group":"global_stats","name":"testfile_02G_2","percentage":45,"size":2147483648,"speed":19986385.67482468,"speedAvg":19337557.3100674,"srcFs":"/mnt/blockstorage/02000m"}],"transfers":0},"time":"2024-05-03T14:57:45.247448+00:00"}
{"level":"info","msg":"\nTransferred:   \t    4.842 GiB / 10 GiB, 48%, 84.038 MiB/s, ETA 1m2s\nTransferred:            0 / 5, 0%\nElapsed time:      1m30.2s\nTransferring:\n *                                testfile_02G_3: 75% /2Gi, 26.972Mi/s, 18s\n *                                testfile_02G_1: 32% /2Gi, 9.797Mi/s, 2m21s\n *                                testfile_02G_4: 78% /2Gi, 28.818Mi/s, 15s\n *                                testfile_02G_2: 56% /2Gi, 19.787Mi/s, 45s\n\n","source":"accounting/stats.go:526","stats":{"bytes":5199593472,"checks":0,"deletedDirs":0,"deletes":0,"elapsedTime":90.246932067,"errors":0,"eta":62,"fatalError":false,"renames":0,"retryError":false,"serverSideCopies":0,"serverSideCopyBytes":0,"serverSideMoveBytes":0,"serverSideMoves":0,"speed":88120243.6185482,"totalBytes":10737418240,"totalChecks":0,"totalTransfers":5,"transferTime":89.926355068,"transferring":[{"bytes":1625292800,"dstFs":"e2-s3perf-20240501-sg:e2-s3perf-20240501-sg/02000m","eta":18,"group":"global_stats","name":"testfile_02G_3","percentage":75,"size":2147483648,"speed":28071181.97913172,"speedAvg":28281816.606303684,"srcFs":"/mnt/blockstorage/02000m"},{"bytes":692060160,"dstFs":"e2-s3perf-20240501-sg:e2-s3perf-20240501-sg/02000m","eta":141,"group":"global_stats","name":"testfile_02G_1","percentage":32,"size":2147483648,"speed":11860129.020907959,"speedAvg":10272603.604802325,"srcFs":"/mnt/blockstorage/02000m"},{"bytes":1676378112,"dstFs":"e2-s3perf-20240501-sg:e2-s3perf-20240501-sg/02000m","eta":15,"group":"global_stats","name":"testfile_02G_4","percentage":78,"size":2147483648,"speed":28974264.042302318,"speedAvg":30218153.64515873,"srcFs":"/mnt/blockstorage/02000m"},{"bytes":1205862400,"dstFs":"e2-s3perf-20240501-sg:e2-s3perf-20240501-sg/02000m","eta":45,"group":"global_stats","name":"testfile_02G_2","percentage":56,"size":2147483648,"speed":20510420.114588577,"speedAvg":20747958.04007111,"srcFs":"/mnt/blockstorage/02000m"}],"transfers":0},"time":"2024-05-03T14:57:55.248652+00:00"}
{"level":"info","msg":"\nTransferred:   \t    5.686 GiB / 10 GiB, 57%, 85.043 MiB/s, ETA 51s\nTransferred:            0 / 5, 0%\nElapsed time:      1m40.2s\nTransferring:\n *                                testfile_02G_3: 88% /2Gi, 26.932Mi/s, 8s\n *                                testfile_02G_1: 38% /2Gi, 11.840Mi/s, 1m45s\n *                                testfile_02G_4: 91% /2Gi, 27.664Mi/s, 6s\n *                                testfile_02G_2: 65% /2Gi, 19.520Mi/s, 35s\n\n","source":"accounting/stats.go:526","stats":{"bytes":6104973312,"checks":0,"deletedDirs":0,"deletes":0,"elapsedTime":100.246508328,"errors":0,"eta":51,"fatalError":false,"renames":0,"retryError":false,"serverSideCopies":0,"serverSideCopyBytes":0,"serverSideMoveBytes":0,"serverSideMoves":0,"speed":89174220.1751053,"totalBytes":10737418240,"totalChecks":0,"totalTransfers":5,"transferTime":99.925954925,"transferring":[{"bytes":1903165440,"dstFs":"e2-s3perf-20240501-sg:e2-s3perf-20240501-sg/02000m","eta":8,"group":"global_stats","name":"testfile_02G_3","percentage":88,"size":2147483648,"speed":28029568.208720885,"speedAvg":28240361.89213112,"srcFs":"/mnt/blockstorage/02000m"},{"bytes":833617920,"dstFs":"e2-s3perf-20240501-sg:e2-s3perf-20240501-sg/02000m","eta":105,"group":"global_stats","name":"testfile_02G_1","percentage":38,"size":2147483648,"speed":12196076.827454932,"speedAvg":12415530.34307651,"srcFs":"/mnt/blockstorage/02000m"},{"bytes":1954217984,"dstFs":"e2-s3perf-20240501-sg:e2-s3perf-20240501-sg/02000m","eta":6,"group":"global_stats","name":"testfile_02G_4","percentage":91,"size":2147483648,"speed":28799076.777873162,"speedAvg":29008143.856155273,"srcFs":"/mnt/blockstorage/02000m"},{"bytes":1413971968,"dstFs":"e2-s3perf-20240501-sg:e2-s3perf-20240501-sg/02000m","eta":35,"group":"global_stats","name":"testfile_02G_2","percentage":65,"size":2147483648,"speed":20554290.121345125,"speedAvg":20468374.267835706,"srcFs":"/mnt/blockstorage/02000m"}],"transfers":0},"time":"2024-05-03T14:58:05.247512+00:00"}
{"level":"info","msg":"\nTransferred:   \t    6.427 GiB / 10 GiB, 64%, 82.901 MiB/s, ETA 44s\nTransferred:            0 / 5, 0%\nElapsed time:      1m50.2s\nTransferring:\n *                                testfile_02G_3:100% /2Gi, 25.481Mi/s, 0s\n *                                testfile_02G_1: 42% /2Gi, 10.357Mi/s, 1m52s\n *                                testfile_02G_4:100% /2Gi, 23.046Mi/s, 0s\n *                                testfile_02G_2: 78% /2Gi, 22.930Mi/s, 19s\n\n","source":"accounting/stats.go:526","stats":{"bytes":6900678656,"checks":0,"deletedDirs":0,"deletes":0,"elapsedTime":110.247179442,"errors":0,"eta":44,"fatalError":false,"renames":0,"retryError":false,"serverSideCopies":0,"serverSideCopyBytes":0,"serverSideMoveBytes":0,"serverSideMoves":0,"speed":86928008.23231818,"totalBytes":10737418240,"totalChecks":0,"totalTransfers":5,"transferTime":109.92649878,"transferring":[{"bytes":2147483648,"dstFs":"e2-s3perf-20240501-sg:e2-s3perf-20240501-sg/02000m","eta":0,"group":"global_stats","name":"testfile_02G_3","percentage":100,"size":2147483648,"speed":27567453.611591395,"speedAvg":26719184.024395436,"srcFs":"/mnt/blockstorage/02000m"},{"bytes":922746880,"dstFs":"e2-s3perf-20240501-sg:e2-s3perf-20240501-sg/02000m","eta":112,"group":"global_stats","name":"testfile_02G_1","percentage":42,"size":2147483648,"speed":11776928.157446928,"speedAvg":10860387.849551892,"srcFs":"/mnt/blockstorage/02000m"},{"bytes":2147483648,"dstFs":"e2-s3perf-20240501-sg:e2-s3perf-20240501-sg/02000m","eta":0,"group":"global_stats","name":"testfile_02G_4","percentage":100,"size":2147483648,"speed":27582146.186262425,"speedAvg":24165421.106376965,"srcFs":"/mnt/blockstorage/02000m"},{"bytes":1682964480,"dstFs":"e2-s3perf-20240501-sg:e2-s3perf-20240501-sg/02000m","eta":19,"group":"global_stats","name":"testfile_02G_2","percentage":78,"size":2147483648,"speed":21359344.80368083,"speedAvg":24043622.594179895,"srcFs":"/mnt/blockstorage/02000m"}],"transfers":0},"time":"2024-05-03T14:58:15.248736+00:00"}
{"level":"info","msg":"Multi-thread Copied (new)","object":"testfile_02G_4","objectType":"*local.Object","size":2147483648,"source":"operations/copy.go:360","time":"2024-05-03T14:58:16.423422+00:00"}
{"level":"info","msg":"Multi-thread Copied (new)","object":"testfile_02G_3","objectType":"*local.Object","size":2147483648,"source":"operations/copy.go:360","time":"2024-05-03T14:58:21.725878+00:00"}
{"level":"info","msg":"\nTransferred:   \t    6.739 GiB / 8 GiB, 84%, 58.005 MiB/s, ETA 22s\nTransferred:            2 / 5, 40%\nElapsed time:       2m0.2s\nTransferring:\n *                                testfile_02G_1: 46% /2Gi, 9.030Mi/s, 2m1s\n *                                testfile_02G_2: 90% /2Gi, 22.926Mi/s, 8s\n *                                testfile_02G_5: transferring\n\n","source":"accounting/stats.go:526","stats":{"bytes":7236222976,"checks":0,"deletedDirs":0,"deletes":0,"elapsedTime":120.2464862,"errors":0,"eta":22,"fatalError":false,"renames":0,"retryError":false,"serverSideCopies":0,"serverSideCopyBytes":0,"serverSideMoveBytes":0,"serverSideMoves":0,"speed":60823164.12740838,"totalBytes":8589934592,"totalChecks":0,"totalTransfers":5,"transferTime":119.925977479,"transferring":[{"bytes":1001390080,"dstFs":"e2-s3perf-20240501-sg:e2-s3perf-20240501-sg/02000m","eta":121,"group":"global_stats","name":"testfile_02G_1","percentage":46,"size":2147483648,"speed":11334185.68456794,"speedAvg":9469120.622618709,"srcFs":"/mnt/blockstorage/02000m"},{"bytes":1939865600,"dstFs":"e2-s3perf-20240501-sg:e2-s3perf-20240501-sg/02000m","eta":8,"group":"global_stats","name":"testfile_02G_2","percentage":90,"size":2147483648,"speed":21847290.472168505,"speedAvg":24040139.50318888,"srcFs":"/mnt/blockstorage/02000m"},{"dstFs":"e2-s3perf-20240501-sg:e2-s3perf-20240501-sg/02000m","name":"testfile_02G_5","size":2147483648,"srcFs":"/mnt/blockstorage/02000m"}],"transfers":2},"time":"2024-05-03T14:58:25.247518+00:00"}
{"level":"info","msg":"\nTransferred:   \t    7.120 GiB / 10 GiB, 71%, 49.635 MiB/s, ETA 59s\nTransferred:            2 / 5, 40%\nElapsed time:      2m10.2s\nTransferring:\n *                                testfile_02G_1: 53% /2Gi, 11.679Mi/s, 1m21s\n *                                testfile_02G_2: 96% /2Gi, 18.417Mi/s, 3s\n *                                testfile_02G_5:  5% /2Gi, 38.332Mi/s, 50s\n\n","source":"accounting/stats.go:526","stats":{"bytes":7645167616,"checks":0,"deletedDirs":0,"deletes":0,"elapsedTime":130.246415713,"errors":0,"eta":59,"fatalError":false,"renames":0,"retryError":false,"serverSideCopies":0,"serverSideCopyBytes":0,"serverSideMoveBytes":0,"serverSideMoves":0,"speed":52045733.876915954,"totalBytes":10737418240,"totalChecks":0,"totalTransfers":5,"transferTime":129.92590574,"transferring":[{"bytes":1148190720,"dstFs":"e2-s3perf-20240501-sg:e2-s3perf-20240501-sg/02000m","eta":81,"group":"global_stats","name":"testfile_02G_1","percentage":53,"size":2147483648,"speed":11674391.647737905,"speedAvg":12246729.916135894,"srcFs":"/mnt/blockstorage/02000m"},{"bytes":2076180480,"dstFs":"e2-s3perf-20240501-sg:e2-s3perf-20240501-sg/02000m","eta":3,"group":"global_stats","name":"testfile_02G_2","percentage":96,"size":2147483648,"speed":21015680.934099432,"speedAvg":19311523.701524988,"srcFs":"/mnt/blockstorage/02000m"},{"bytes":125829120,"dstFs":"e2-s3perf-20240501-sg:e2-s3perf-20240501-sg/02000m","eta":50,"group":"global_stats","name":"testfile_02G_5","percentage":5,"size":2147483648,"speed":41632863.09640151,"speedAvg":40194151.291586906,"srcFs":"/mnt/blockstorage/02000m"}],"transfers":2},"time":"2024-05-03T14:58:35.247487+00:00"}
{"level":"info","msg":"\nTransferred:   \t    7.738 GiB / 10 GiB, 77%, 55.476 MiB/s, ETA 41s\nTransferred:            2 / 5, 40%\nElapsed time:      2m20.2s\nTransferring:\n *                                testfile_02G_1: 60% /2Gi, 12.755Mi/s, 1m3s\n *                                testfile_02G_2:100% /2Gi, 13.012Mi/s, 0s\n *                                testfile_02G_5: 26% /2Gi, 41.151Mi/s, 36s\n\n","source":"accounting/stats.go:526","stats":{"bytes":8308916224,"checks":0,"deletedDirs":0,"deletes":0,"elapsedTime":140.246490022,"errors":0,"eta":41,"fatalError":false,"renames":0,"retryError":false,"serverSideCopies":0,"serverSideCopyBytes":0,"serverSideMoveBytes":0,"serverSideMoves":0,"speed":58170857.31547111,"totalBytes":10737418240,"totalChecks":0,"totalTransfers":5,"transferTime":139.925964039,"transferring":[{"bytes":1300234240,"dstFs":"e2-s3perf-20240501-sg:e2-s3perf-20240501-sg/02000m","eta":63,"group":"global_stats","name":"testfile_02G_1","percentage":60,"size":2147483648,"speed":12000172.83009289,"speedAvg":13374950.048376331,"srcFs":"/mnt/blockstorage/02000m"},{"bytes":2147483648,"dstFs":"e2-s3perf-20240501-sg:e2-s3perf-20240501-sg/02000m","eta":0,"group":"global_stats","name":"testfile_02G_2","percentage":100,"size":2147483648,"speed":19739346.450052116,"speedAvg":13643688.181527324,"srcFs":"/mnt/blockstorage/02000m"},{"bytes":566231040,"dstFs":"e2-s3perf-20240501-sg:e2-s3perf-20240501-sg/02000m","eta":36,"group":"global_stats","name":"testfile_02G_5","percentage":26,"size":2147483648,"speed":43481261.91912986,"speedAvg":43149564.60466225,"srcFs":"/mnt/blockstorage/02000m"}],"transfers":2},"time":"2024-05-03T14:58:45.24754+00:00"}
{"level":"info","msg":"Multi-thread Copied (new)","object":"testfile_02G_2","objectType":"*local.Object","size":2147483648,"source":"operations/copy.go:360","time":"2024-05-03T14:58:51.093025+00:00"}
{"level":"info","msg":"\nTransferred:   \t    8.300 GiB / 10 GiB, 83%, 57.006 MiB/s, ETA 30s\nTransferred:            3 / 5, 60%\nElapsed time:      2m30.2s\nTransferring:\n *                                testfile_02G_1: 67% /2Gi, 13.386Mi/s, 49s\n *                                testfile_02G_5: 47% /2Gi, 41.694Mi/s, 25s\n\n","source":"accounting/stats.go:526","stats":{"bytes":8911847424,"checks":0,"deletedDirs":0,"deletes":0,"elapsedTime":150.247387068,"errors":0,"eta":30,"fatalError":false,"renames":0,"retryError":false,"serverSideCopies":0,"serverSideCopyBytes":0,"serverSideMoveBytes":0,"serverSideMoves":0,"speed":59774858.02929402,"totalBytes":10737418240,"totalChecks":0,"totalTransfers":5,"transferTime":149.926878558,"transferring":[{"bytes":1452277760,"dstFs":"e2-s3perf-20240501-sg:e2-s3perf-20240501-sg/02000m","eta":49,"group":"global_stats","name":"testfile_02G_1","percentage":67,"size":2147483648,"speed":12270813.644803328,"speedAvg":14036401.397858916,"srcFs":"/mnt/blockstorage/02000m"},{"bytes":1017118720,"dstFs":"e2-s3perf-20240501-sg:e2-s3perf-20240501-sg/02000m","eta":25,"group":"global_stats","name":"testfile_02G_5","percentage":47,"size":2147483648,"speed":44177760.0792783,"speedAvg":43719244.138230965,"srcFs":"/mnt/blockstorage/02000m"}],"transfers":3},"time":"2024-05-03T14:58:55.248404+00:00"}
{"level":"info","msg":"\nTransferred:   \t    8.754 GiB / 10 GiB, 88%, 52.042 MiB/s, ETA 24s\nTransferred:            3 / 5, 60%\nElapsed time:      2m40.2s\nTransferring:\n *                                testfile_02G_1: 70% /2Gi, 10.453Mi/s, 57s\n *                                testfile_02G_5: 66% /2Gi, 41.205Mi/s, 16s\n\n","source":"accounting/stats.go:526","stats":{"bytes":9399435264,"checks":0,"deletedDirs":0,"deletes":0,"elapsedTime":160.247104708,"errors":0,"eta":24,"fatalError":false,"renames":0,"retryError":false,"serverSideCopies":0,"serverSideCopyBytes":0,"serverSideMoveBytes":0,"serverSideMoves":0,"speed":54569723.42063942,"totalBytes":10737418240,"totalChecks":0,"totalTransfers":5,"transferTime":159.926574819,"transferring":[{"bytes":1520435200,"dstFs":"e2-s3perf-20240501-sg:e2-s3perf-20240501-sg/02000m","eta":57,"group":"global_stats","name":"testfile_02G_1","percentage":70,"size":2147483648,"speed":11845832.49888203,"speedAvg":10960249.76801839,"srcFs":"/mnt/blockstorage/02000m"},{"bytes":1436549120,"dstFs":"e2-s3perf-20240501-sg:e2-s3perf-20240501-sg/02000m","eta":16,"group":"global_stats","name":"testfile_02G_5","percentage":66,"size":2147483648,"speed":43501437.72918151,"speedAvg":43206316.38952034,"srcFs":"/mnt/blockstorage/02000m"}],"transfers":3},"time":"2024-05-03T14:59:05.248138+00:00"}
{"level":"info","msg":"\nTransferred:   \t    9.292 GiB / 10 GiB, 93%, 54.243 MiB/s, ETA 13s\nTransferred:            3 / 5, 60%\nElapsed time:      2m50.2s\nTransferring:\n *                                testfile_02G_1: 76% /2Gi, 11.238Mi/s, 42s\n *                                testfile_02G_5: 87% /2Gi, 41.809Mi/s, 5s\n\n","source":"accounting/stats.go:526","stats":{"bytes":9977102336,"checks":0,"deletedDirs":0,"deletes":0,"elapsedTime":170.253168553,"errors":0,"eta":13,"fatalError":false,"renames":0,"retryError":false,"serverSideCopies":0,"serverSideCopyBytes":0,"serverSideMoveBytes":0,"serverSideMoves":0,"speed":56877482.81366128,"totalBytes":10737418240,"totalChecks":0,"totalTransfers":5,"transferTime":169.932663239,"transferring":[{"bytes":1646264320,"dstFs":"e2-s3perf-20240501-sg:e2-s3perf-20240501-sg/02000m","eta":42,"group":"global_stats","name":"testfile_02G_1","percentage":76,"size":2147483648,"speed":11898582.993772237,"speedAvg":11784272.495365173,"srcFs":"/mnt/blockstorage/02000m"},{"bytes":1888419840,"dstFs":"e2-s3perf-20240501-sg:e2-s3perf-20240501-sg/02000m","eta":5,"group":"global_stats","name":"testfile_02G_5","percentage":87,"size":2147483648,"speed":43886996.05966061,"speedAvg":43839402.06391292,"srcFs":"/mnt/blockstorage/02000m"}],"transfers":3},"time":"2024-05-03T14:59:15.255345+00:00"}
{"level":"info","msg":"Multi-thread Copied (new)","object":"testfile_02G_5","objectType":"*local.Object","size":2147483648,"source":"operations/copy.go:360","time":"2024-05-03T14:59:24.59901+00:00"}
{"level":"info","msg":"\nTransferred:   \t    9.675 GiB / 10 GiB, 97%, 48.052 MiB/s, ETA 6s\nTransferred:            4 / 5, 80%\nElapsed time:       3m0.2s\nTransferring:\n *                                testfile_02G_1: 83% /2Gi, 12.956Mi/s, 25s\n\n","source":"accounting/stats.go:526","stats":{"bytes":10388242432,"checks":0,"deletedDirs":0,"deletes":0,"elapsedTime":180.246544281,"errors":0,"eta":6,"fatalError":false,"renames":0,"retryError":false,"serverSideCopies":0,"serverSideCopyBytes":0,"serverSideMoveBytes":0,"serverSideMoves":0,"speed":50386373.36854381,"totalBytes":10737418240,"totalChecks":0,"totalTransfers":5,"transferTime":179.926028828,"transferring":[{"bytes":1798307840,"dstFs":"e2-s3perf-20240501-sg:e2-s3perf-20240501-sg/02000m","eta":25,"group":"global_stats","name":"testfile_02G_1","percentage":83,"size":2147483648,"speed":12121948.95823289,"speedAvg":13585377.212228388,"srcFs":"/mnt/blockstorage/02000m"}],"transfers":4},"time":"2024-05-03T14:59:25.24764+00:00"}
{"level":"info","msg":"\nTransferred:   \t    9.812 GiB / 10 GiB, 98%, 31.535 MiB/s, ETA 6s\nTransferred:            4 / 5, 80%\nElapsed time:      3m10.2s\nTransferring:\n *                                testfile_02G_1: 90% /2Gi, 12.849Mi/s, 15s\n\n","source":"accounting/stats.go:526","stats":{"bytes":10535043072,"checks":0,"deletedDirs":0,"deletes":0,"elapsedTime":190.246816643,"errors":0,"eta":6,"fatalError":false,"renames":0,"retryError":false,"serverSideCopies":0,"serverSideCopyBytes":0,"serverSideMoveBytes":0,"serverSideMoves":0,"speed":33066537.078414783,"totalBytes":10737418240,"totalChecks":0,"totalTransfers":5,"transferTime":189.926314406,"transferring":[{"bytes":1945108480,"dstFs":"e2-s3perf-20240501-sg:e2-s3perf-20240501-sg/02000m","eta":15,"group":"global_stats","name":"testfile_02G_1","percentage":90,"size":2147483648,"speed":12283477.152915724,"speedAvg":13472936.44750495,"srcFs":"/mnt/blockstorage/02000m"}],"transfers":4},"time":"2024-05-03T14:59:35.247763+00:00"}
{"level":"info","msg":"\nTransferred:   \t    9.938 GiB / 10 GiB, 99%, 23.398 MiB/s, ETA 2s\nTransferred:            4 / 5, 80%\nElapsed time:      3m20.2s\nTransferring:\n *                                testfile_02G_1: 96% /2Gi, 13.411Mi/s, 4s\n\n","source":"accounting/stats.go:526","stats":{"bytes":10671357952,"checks":0,"deletedDirs":0,"deletes":0,"elapsedTime":200.246342073,"errors":0,"eta":2,"fatalError":false,"renames":0,"retryError":false,"serverSideCopies":0,"serverSideCopyBytes":0,"serverSideMoveBytes":0,"serverSideMoves":0,"speed":24534152.463467866,"totalBytes":10737418240,"totalChecks":0,"totalTransfers":5,"transferTime":199.925840395,"transferring":[{"bytes":2081423360,"dstFs":"e2-s3perf-20240501-sg:e2-s3perf-20240501-sg/02000m","eta":4,"group":"global_stats","name":"testfile_02G_1","percentage":96,"size":2147483648,"speed":12363583.348159533,"speedAvg":14062113.815559221,"srcFs":"/mnt/blockstorage/02000m"}],"transfers":4},"time":"2024-05-03T14:59:45.247305+00:00"}
{"level":"info","msg":"\nTransferred:   \t       10 GiB / 10 GiB, 100%, 15.192 MiB/s, ETA 0s\nTransferred:            4 / 5, 80%\nElapsed time:      3m30.2s\nTransferring:\n *                                testfile_02G_1:100% /2Gi, 9.911Mi/s, 0s\n\n","source":"accounting/stats.go:526","stats":{"bytes":10737418240,"checks":0,"deletedDirs":0,"deletes":0,"elapsedTime":210.24723171,"errors":0,"eta":0,"fatalError":false,"renames":0,"retryError":false,"serverSideCopies":0,"serverSideCopyBytes":0,"serverSideMoveBytes":0,"serverSideMoves":0,"speed":15929666.859293729,"totalBytes":10737418240,"totalChecks":0,"totalTransfers":5,"transferTime":209.926724813,"transferring":[{"bytes":2147483648,"dstFs":"e2-s3perf-20240501-sg:e2-s3perf-20240501-sg/02000m","eta":0,"group":"global_stats","name":"testfile_02G_1","percentage":100,"size":2147483648,"speed":12040701.558493042,"speedAvg":10392573.804986235,"srcFs":"/mnt/blockstorage/02000m"}],"transfers":4},"time":"2024-05-03T14:59:55.248195+00:00"}
{"level":"info","msg":"\nTransferred:   \t       10 GiB / 10 GiB, 100%, 7.967 MiB/s, ETA 0s\nTransferred:            4 / 5, 80%\nElapsed time:      3m40.2s\nTransferring:\n *                                testfile_02G_1:100% /2Gi, 5.198Mi/s, 0s\n\n","source":"accounting/stats.go:526","stats":{"bytes":10737418240,"checks":0,"deletedDirs":0,"deletes":0,"elapsedTime":220.246917148,"errors":0,"eta":0,"fatalError":false,"renames":0,"retryError":false,"serverSideCopies":0,"serverSideCopyBytes":0,"serverSideMoveBytes":0,"serverSideMoves":0,"speed":8354480.648393151,"totalBytes":10737418240,"totalChecks":0,"totalTransfers":5,"transferTime":219.926411093,"transferring":[{"bytes":2147483648,"dstFs":"e2-s3perf-20240501-sg:e2-s3perf-20240501-sg/02000m","eta":0,"group":"global_stats","name":"testfile_02G_1","percentage":100,"size":2147483648,"speed":11401454.938208234,"speedAvg":5450494.194742038,"srcFs":"/mnt/blockstorage/02000m"}],"transfers":4},"time":"2024-05-03T15:00:05.247888+00:00"}
{"level":"info","msg":"Multi-thread Copied (new)","object":"testfile_02G_1","objectType":"*local.Object","size":2147483648,"source":"operations/copy.go:360","time":"2024-05-03T15:00:08.919261+00:00"}
{"level":"info","msg":"\nTransferred:   \t       10 GiB / 10 GiB, 100%, 6.155 MiB/s, ETA 0s\nTransferred:            5 / 5, 100%\nElapsed time:      3m43.9s\n\n","source":"accounting/stats.go:526","stats":{"bytes":10737418240,"checks":0,"deletedDirs":0,"deletes":0,"elapsedTime":223.918669148,"errors":0,"eta":0,"fatalError":false,"renames":0,"retryError":false,"serverSideCopies":0,"serverSideCopyBytes":0,"serverSideMoveBytes":0,"serverSideMoves":0,"speed":6453637.433241322,"totalBytes":10737418240,"totalChecks":0,"totalTransfers":5,"transferTime":223.59814538,"transfers":5},"time":"2024-05-03T15:00:08.919598+00:00"}
