{"level":"info","msg":"Copied (new)","object":"testfile_01M_10","objectType":"*local.Object","size":1048576,"source":"operations/copy.go:360","time":"2024-05-04T02:12:21.282248+00:00"}
{"level":"info","msg":"Copied (new)","object":"testfile_01M_1","objectType":"*local.Object","size":1048576,"source":"operations/copy.go:360","time":"2024-05-04T02:12:21.295318+00:00"}
{"level":"info","msg":"Copied (new)","object":"testfile_01M_101","objectType":"*local.Object","size":1048576,"source":"operations/copy.go:360","time":"2024-05-04T02:12:21.317149+00:00"}
{"level":"info","msg":"Copied (new)","object":"testfile_01M_100","objectType":"*local.Object","size":1048576,"source":"operations/copy.go:360","time":"2024-05-04T02:12:21.350567+00:00"}
{"level":"info","msg":"Copied (new)","object":"testfile_01M_102","objectType":"*local.Object","size":1048576,"source":"operations/copy.go:360","time":"2024-05-04T02:12:21.926667+00:00"}
{"level":"info","msg":"Copied (new)","object":"testfile_01M_103","objectType":"*local.Object","size":1048576,"source":"operations/copy.go:360","time":"2024-05-04T02:12:22.08842+00:00"}
{"level":"info","msg":"Copied (new)","object":"testfile_01M_104","objectType":"*local.Object","size":1048576,"source":"operations/copy.go:360","time":"2024-05-04T02:12:22.114849+00:00"}
{"level":"info","msg":"Copied (new)","object":"testfile_01M_108","objectType":"*local.Object","size":1048576,"source":"operations/copy.go:360","time":"2024-05-04T02:12:22.868943+00:00"}
{"level":"info","msg":"Copied (new)","object":"testfile_01M_106","objectType":"*local.Object","size":1048576,"source":"operations/copy.go:360","time":"2024-05-04T02:12:23.299791+00:00"}
{"level":"info","msg":"Copied (new)","object":"testfile_01M_105","objectType":"*local.Object","size":1048576,"source":"operations/copy.go:360","time":"2024-05-04T02:12:23.319018+00:00"}
{"level":"info","msg":"Copied (new)","object":"testfile_01M_107","objectType":"*local.Object","size":1048576,"source":"operations/copy.go:360","time":"2024-05-04T02:12:23.371748+00:00"}
{"level":"info","msg":"Copied (new)","object":"testfile_01M_109","objectType":"*local.Object","size":1048576,"source":"operations/copy.go:360","time":"2024-05-04T02:12:23.650979+00:00"}
{"level":"info","msg":"Copied (new)","object":"testfile_01M_11","objectType":"*local.Object","size":1048576,"source":"operations/copy.go:360","time":"2024-05-04T02:12:24.113381+00:00"}
{"level":"info","msg":"Copied (new)","object":"testfile_01M_110","objectType":"*local.Object","size":1048576,"source":"operations/copy.go:360","time":"2024-05-04T02:12:24.147413+00:00"}
{"level":"info","msg":"Copied (new)","object":"testfile_01M_111","objectType":"*local.Object","size":1048576,"source":"operations/copy.go:360","time":"2024-05-04T02:12:24.152154+00:00"}
{"level":"info","msg":"Copied (new)","object":"testfile_01M_112","objectType":"*local.Object","size":1048576,"source":"operations/copy.go:360","time":"2024-05-04T02:12:24.247844+00:00"}
{"level":"info","msg":"Copied (new)","object":"testfile_01M_113","objectType":"*local.Object","size":1048576,"source":"operations/copy.go:360","time":"2024-05-04T02:12:24.91745+00:00"}
{"level":"info","msg":"Copied (new)","object":"testfile_01M_114","objectType":"*local.Object","size":1048576,"source":"operations/copy.go:360","time":"2024-05-04T02:12:24.937593+00:00"}
{"level":"info","msg":"Copied (new)","object":"testfile_01M_115","objectType":"*local.Object","size":1048576,"source":"operations/copy.go:360","time":"2024-05-04T02:12:24.946219+00:00"}
{"level":"info","msg":"Copied (new)","object":"testfile_01M_116","objectType":"*local.Object","size":1048576,"source":"operations/copy.go:360","time":"2024-05-04T02:12:25.003151+00:00"}
{"level":"info","msg":"Copied (new)","object":"testfile_01M_118","objectType":"*local.Object","size":1048576,"source":"operations/copy.go:360","time":"2024-05-04T02:12:25.537735+00:00"}
{"level":"info","msg":"Copied (new)","object":"testfile_01M_117","objectType":"*local.Object","size":1048576,"source":"operations/copy.go:360","time":"2024-05-04T02:12:25.658654+00:00"}
{"level":"info","msg":"Copied (new)","object":"testfile_01M_12","objectType":"*local.Object","size":1048576,"source":"operations/copy.go:360","time":"2024-05-04T02:12:25.821034+00:00"}
{"level":"info","msg":"Copied (new)","object":"testfile_01M_119","objectType":"*local.Object","size":1048576,"source":"operations/copy.go:360","time":"2024-05-04T02:12:25.838337+00:00"}
{"level":"info","msg":"Copied (new)","object":"testfile_01M_121","objectType":"*local.Object","size":1048576,"source":"operations/copy.go:360","time":"2024-05-04T02:12:26.596343+00:00"}
{"level":"info","msg":"Copied (new)","object":"testfile_01M_120","objectType":"*local.Object","size":1048576,"source":"operations/copy.go:360","time":"2024-05-04T02:12:26.607426+00:00"}
{"level":"info","msg":"Copied (new)","object":"testfile_01M_122","objectType":"*local.Object","size":1048576,"source":"operations/copy.go:360","time":"2024-05-04T02:12:26.651233+00:00"}
{"level":"info","msg":"Copied (new)","object":"testfile_01M_123","objectType":"*local.Object","size":1048576,"source":"operations/copy.go:360","time":"2024-05-04T02:12:26.725425+00:00"}
{"level":"info","msg":"Copied (new)","object":"testfile_01M_124","objectType":"*local.Object","size":1048576,"source":"operations/copy.go:360","time":"2024-05-04T02:12:27.213543+00:00"}
{"level":"info","msg":"Copied (new)","object":"testfile_01M_125","objectType":"*local.Object","size":1048576,"source":"operations/copy.go:360","time":"2024-05-04T02:12:27.374592+00:00"}
{"level":"info","msg":"Copied (new)","object":"testfile_01M_126","objectType":"*local.Object","size":1048576,"source":"operations/copy.go:360","time":"2024-05-04T02:12:27.445844+00:00"}
{"level":"info","msg":"Copied (new)","object":"testfile_01M_127","objectType":"*local.Object","size":1048576,"source":"operations/copy.go:360","time":"2024-05-04T02:12:27.56594+00:00"}
{"level":"info","msg":"Copied (new)","object":"testfile_01M_128","objectType":"*local.Object","size":1048576,"source":"operations/copy.go:360","time":"2024-05-04T02:12:27.9893+00:00"}
{"level":"info","msg":"\nTransferred:   \t       37 MiB / 128 MiB, 29%, 3.778 MiB/s, ETA 24s\nTransferred:           33 / 128, 26%\nElapsed time:        10.8s\nTransferring:\n *                               testfile_01M_13:100% /1Mi, 0/s, -\n *                               testfile_01M_14:100% /1Mi, 0/s, -\n *                               testfile_01M_15:100% /1Mi, 0/s, -\n *                               testfile_01M_16:100% /1Mi, 0/s, -\n\n","source":"accounting/stats.go:526","stats":{"bytes":38797312,"checks":0,"deletedDirs":0,"deletes":0,"elapsedTime":10.881910219,"errors":0,"eta":24,"fatalError":false,"renames":0,"retryError":false,"serverSideCopies":0,"serverSideCopyBytes":0,"serverSideMoveBytes":0,"serverSideMoves":0,"speed":3961060.203323541,"totalBytes":134217728,"totalChecks":0,"totalTransfers":128,"transferTime":9.756861965,"transferring":[{"bytes":1048576,"dstFs":"e2-s3perf-20240501-par:e2-s3perf-20240501-par/00001m","eta":null,"group":"global_stats","name":"testfile_01M_13","percentage":100,"size":1048576,"speed":1328653.1521318972,"speedAvg":0,"srcFs":"/mnt/blockstorage/00001m"},{"bytes":1048576,"dstFs":"e2-s3perf-20240501-par:e2-s3perf-20240501-par/00001m","eta":null,"group":"global_stats","name":"testfile_01M_14","percentage":100,"size":1048576,"speed":1460849.282148201,"speedAvg":0,"srcFs":"/mnt/blockstorage/00001m"},{"bytes":1048576,"dstFs":"e2-s3perf-20240501-par:e2-s3perf-20240501-par/00001m","eta":null,"group":"global_stats","name":"testfile_01M_15","percentage":100,"size":1048576,"speed":1753348.8052377524,"speedAvg":0,"srcFs":"/mnt/blockstorage/00001m"},{"bytes":1048576,"dstFs":"e2-s3perf-20240501-par:e2-s3perf-20240501-par/00001m","eta":null,"group":"global_stats","name":"testfile_01M_16","percentage":100,"size":1048576,"speed":6061145.630836522,"speedAvg":0,"srcFs":"/mnt/blockstorage/00001m"}],"transfers":33},"time":"2024-05-04T02:12:28.173118+00:00"}
{"level":"info","msg":"Copied (new)","object":"testfile_01M_14","objectType":"*local.Object","size":1048576,"source":"operations/copy.go:360","time":"2024-05-04T02:12:28.269096+00:00"}
{"level":"info","msg":"Copied (new)","object":"testfile_01M_13","objectType":"*local.Object","size":1048576,"source":"operations/copy.go:360","time":"2024-05-04T02:12:28.28487+00:00"}
{"level":"info","msg":"Copied (new)","object":"testfile_01M_15","objectType":"*local.Object","size":1048576,"source":"operations/copy.go:360","time":"2024-05-04T02:12:28.380473+00:00"}
{"level":"info","msg":"Copied (new)","object":"testfile_01M_16","objectType":"*local.Object","size":1048576,"source":"operations/copy.go:360","time":"2024-05-04T02:12:28.587681+00:00"}
{"level":"info","msg":"Copied (new)","object":"testfile_01M_2","objectType":"*local.Object","size":1048576,"source":"operations/copy.go:360","time":"2024-05-04T02:12:29.184101+00:00"}
{"level":"info","msg":"Copied (new)","object":"testfile_01M_17","objectType":"*local.Object","size":1048576,"source":"operations/copy.go:360","time":"2024-05-04T02:12:29.281097+00:00"}
{"level":"info","msg":"Copied (new)","object":"testfile_01M_19","objectType":"*local.Object","size":1048576,"source":"operations/copy.go:360","time":"2024-05-04T02:12:29.313839+00:00"}
{"level":"info","msg":"Copied (new)","object":"testfile_01M_18","objectType":"*local.Object","size":1048576,"source":"operations/copy.go:360","time":"2024-05-04T02:12:29.5207+00:00"}
{"level":"info","msg":"Copied (new)","object":"testfile_01M_20","objectType":"*local.Object","size":1048576,"source":"operations/copy.go:360","time":"2024-05-04T02:12:29.782014+00:00"}
{"level":"info","msg":"Copied (new)","object":"testfile_01M_21","objectType":"*local.Object","size":1048576,"source":"operations/copy.go:360","time":"2024-05-04T02:12:30.047574+00:00"}
{"level":"info","msg":"Copied (new)","object":"testfile_01M_22","objectType":"*local.Object","size":1048576,"source":"operations/copy.go:360","time":"2024-05-04T02:12:30.11089+00:00"}
{"level":"info","msg":"Copied (new)","object":"testfile_01M_23","objectType":"*local.Object","size":1048576,"source":"operations/copy.go:360","time":"2024-05-04T02:12:30.461419+00:00"}
{"level":"info","msg":"Copied (new)","object":"testfile_01M_24","objectType":"*local.Object","size":1048576,"source":"operations/copy.go:360","time":"2024-05-04T02:12:30.556398+00:00"}
{"level":"info","msg":"Copied (new)","object":"testfile_01M_25","objectType":"*local.Object","size":1048576,"source":"operations/copy.go:360","time":"2024-05-04T02:12:30.903601+00:00"}
{"level":"info","msg":"Copied (new)","object":"testfile_01M_26","objectType":"*local.Object","size":1048576,"source":"operations/copy.go:360","time":"2024-05-04T02:12:31.103384+00:00"}
{"level":"info","msg":"Copied (new)","object":"testfile_01M_27","objectType":"*local.Object","size":1048576,"source":"operations/copy.go:360","time":"2024-05-04T02:12:31.441197+00:00"}
{"level":"info","msg":"Copied (new)","object":"testfile_01M_28","objectType":"*local.Object","size":1048576,"source":"operations/copy.go:360","time":"2024-05-04T02:12:31.497831+00:00"}
{"level":"info","msg":"Copied (new)","object":"testfile_01M_29","objectType":"*local.Object","size":1048576,"source":"operations/copy.go:360","time":"2024-05-04T02:12:31.686403+00:00"}
{"level":"info","msg":"Copied (new)","object":"testfile_01M_3","objectType":"*local.Object","size":1048576,"source":"operations/copy.go:360","time":"2024-05-04T02:12:32.026083+00:00"}
{"level":"info","msg":"Copied (new)","object":"testfile_01M_30","objectType":"*local.Object","size":1048576,"source":"operations/copy.go:360","time":"2024-05-04T02:12:32.396875+00:00"}
{"level":"info","msg":"Copied (new)","object":"testfile_01M_32","objectType":"*local.Object","size":1048576,"source":"operations/copy.go:360","time":"2024-05-04T02:12:32.446388+00:00"}
{"level":"info","msg":"Copied (new)","object":"testfile_01M_31","objectType":"*local.Object","size":1048576,"source":"operations/copy.go:360","time":"2024-05-04T02:12:32.48027+00:00"}
{"level":"info","msg":"Copied (new)","object":"testfile_01M_33","objectType":"*local.Object","size":1048576,"source":"operations/copy.go:360","time":"2024-05-04T02:12:32.888768+00:00"}
{"level":"info","msg":"Copied (new)","object":"testfile_01M_34","objectType":"*local.Object","size":1048576,"source":"operations/copy.go:360","time":"2024-05-04T02:12:33.139552+00:00"}
{"level":"info","msg":"Copied (new)","object":"testfile_01M_35","objectType":"*local.Object","size":1048576,"source":"operations/copy.go:360","time":"2024-05-04T02:12:33.242674+00:00"}
{"level":"info","msg":"Copied (new)","object":"testfile_01M_36","objectType":"*local.Object","size":1048576,"source":"operations/copy.go:360","time":"2024-05-04T02:12:33.295305+00:00"}
{"level":"info","msg":"Copied (new)","object":"testfile_01M_37","objectType":"*local.Object","size":1048576,"source":"operations/copy.go:360","time":"2024-05-04T02:12:33.862181+00:00"}
{"level":"info","msg":"Copied (new)","object":"testfile_01M_38","objectType":"*local.Object","size":1048576,"source":"operations/copy.go:360","time":"2024-05-04T02:12:33.881816+00:00"}
{"level":"info","msg":"Copied (new)","object":"testfile_01M_39","objectType":"*local.Object","size":1048576,"source":"operations/copy.go:360","time":"2024-05-04T02:12:33.992191+00:00"}
{"level":"info","msg":"Copied (new)","object":"testfile_01M_4","objectType":"*local.Object","size":1048576,"source":"operations/copy.go:360","time":"2024-05-04T02:12:34.102037+00:00"}
{"level":"info","msg":"Copied (new)","object":"testfile_01M_41","objectType":"*local.Object","size":1048576,"source":"operations/copy.go:360","time":"2024-05-04T02:12:34.614524+00:00"}
{"level":"info","msg":"Copied (new)","object":"testfile_01M_40","objectType":"*local.Object","size":1048576,"source":"operations/copy.go:360","time":"2024-05-04T02:12:34.638747+00:00"}
{"level":"info","msg":"Copied (new)","object":"testfile_01M_42","objectType":"*local.Object","size":1048576,"source":"operations/copy.go:360","time":"2024-05-04T02:12:34.74389+00:00"}
{"level":"info","msg":"Copied (new)","object":"testfile_01M_43","objectType":"*local.Object","size":1048576,"source":"operations/copy.go:360","time":"2024-05-04T02:12:34.896766+00:00"}
{"level":"info","msg":"Copied (new)","object":"testfile_01M_46","objectType":"*local.Object","size":1048576,"source":"operations/copy.go:360","time":"2024-05-04T02:12:35.555563+00:00"}
{"level":"info","msg":"Copied (new)","object":"testfile_01M_44","objectType":"*local.Object","size":1048576,"source":"operations/copy.go:360","time":"2024-05-04T02:12:35.555645+00:00"}
{"level":"info","msg":"Copied (new)","object":"testfile_01M_45","objectType":"*local.Object","size":1048576,"source":"operations/copy.go:360","time":"2024-05-04T02:12:35.577572+00:00"}
{"level":"info","msg":"Copied (new)","object":"testfile_01M_47","objectType":"*local.Object","size":1048576,"source":"operations/copy.go:360","time":"2024-05-04T02:12:35.680217+00:00"}
{"level":"info","msg":"Copied (new)","object":"testfile_01M_49","objectType":"*local.Object","size":1048576,"source":"operations/copy.go:360","time":"2024-05-04T02:12:36.293893+00:00"}
{"level":"info","msg":"Copied (new)","object":"testfile_01M_48","objectType":"*local.Object","size":1048576,"source":"operations/copy.go:360","time":"2024-05-04T02:12:36.306857+00:00"}
{"level":"info","msg":"Copied (new)","object":"testfile_01M_5","objectType":"*local.Object","size":1048576,"source":"operations/copy.go:360","time":"2024-05-04T02:12:36.344188+00:00"}
{"level":"info","msg":"Copied (new)","object":"testfile_01M_50","objectType":"*local.Object","size":1048576,"source":"operations/copy.go:360","time":"2024-05-04T02:12:36.457734+00:00"}
{"level":"info","msg":"Copied (new)","object":"testfile_01M_51","objectType":"*local.Object","size":1048576,"source":"operations/copy.go:360","time":"2024-05-04T02:12:37.039862+00:00"}
{"level":"info","msg":"Copied (new)","object":"testfile_01M_52","objectType":"*local.Object","size":1048576,"source":"operations/copy.go:360","time":"2024-05-04T02:12:37.062243+00:00"}
{"level":"info","msg":"Copied (new)","object":"testfile_01M_53","objectType":"*local.Object","size":1048576,"source":"operations/copy.go:360","time":"2024-05-04T02:12:37.359151+00:00"}
{"level":"info","msg":"Copied (new)","object":"testfile_01M_54","objectType":"*local.Object","size":1048576,"source":"operations/copy.go:360","time":"2024-05-04T02:12:37.371754+00:00"}
{"level":"info","msg":"Copied (new)","object":"testfile_01M_56","objectType":"*local.Object","size":1048576,"source":"operations/copy.go:360","time":"2024-05-04T02:12:37.843449+00:00"}
{"level":"info","msg":"Copied (new)","object":"testfile_01M_55","objectType":"*local.Object","size":1048576,"source":"operations/copy.go:360","time":"2024-05-04T02:12:37.843591+00:00"}
{"level":"info","msg":"Copied (new)","object":"testfile_01M_57","objectType":"*local.Object","size":1048576,"source":"operations/copy.go:360","time":"2024-05-04T02:12:38.125387+00:00"}
{"level":"info","msg":"Copied (new)","object":"testfile_01M_58","objectType":"*local.Object","size":1048576,"source":"operations/copy.go:360","time":"2024-05-04T02:12:38.145939+00:00"}
{"level":"info","msg":"\nTransferred:   \t       87 MiB / 128 MiB, 68%, 4.393 MiB/s, ETA 9s\nTransferred:           83 / 128, 65%\nElapsed time:        20.8s\nTransferring:\n *                               testfile_01M_59:100% /1Mi, 0/s, -\n *                                testfile_01M_6:100% /1Mi, 0/s, -\n *                               testfile_01M_60:100% /1Mi, 0/s, -\n *                               testfile_01M_61:100% /1Mi, 0/s, -\n\n","source":"accounting/stats.go:526","stats":{"bytes":91226112,"checks":0,"deletedDirs":0,"deletes":0,"elapsedTime":20.881846506,"errors":0,"eta":9,"fatalError":false,"renames":0,"retryError":false,"serverSideCopies":0,"serverSideCopyBytes":0,"serverSideMoveBytes":0,"serverSideMoves":0,"speed":4606112.644795068,"totalBytes":134217728,"totalChecks":0,"totalTransfers":128,"transferTime":19.756791578,"transferring":[{"bytes":1048576,"dstFs":"e2-s3perf-20240501-par:e2-s3perf-20240501-par/00001m","eta":null,"group":"global_stats","name":"testfile_01M_59","percentage":100,"size":1048576,"speed":3281246.5094299866,"speedAvg":0,"srcFs":"/mnt/blockstorage/00001m"},{"bytes":1048576,"dstFs":"e2-s3perf-20240501-par:e2-s3perf-20240501-par/00001m","eta":null,"group":"global_stats","name":"testfile_01M_6","percentage":100,"size":1048576,"speed":3255759.5016071373,"speedAvg":0,"srcFs":"/mnt/blockstorage/00001m"},{"bytes":1048576,"dstFs":"e2-s3perf-20240501-par:e2-s3perf-20240501-par/00001m","eta":null,"group":"global_stats","name":"testfile_01M_60","percentage":100,"size":1048576,"speed":26743439.386530325,"speedAvg":0,"srcFs":"/mnt/blockstorage/00001m"},{"bytes":1048576,"dstFs":"e2-s3perf-20240501-par:e2-s3perf-20240501-par/00001m","eta":null,"group":"global_stats","name":"testfile_01M_61","percentage":100,"size":1048576,"speed":63467748.705784544,"speedAvg":0,"srcFs":"/mnt/blockstorage/00001m"}],"transfers":83},"time":"2024-05-04T02:12:38.173042+00:00"}
{"level":"info","msg":"Copied (new)","object":"testfile_01M_59","objectType":"*local.Object","size":1048576,"source":"operations/copy.go:360","time":"2024-05-04T02:12:38.584333+00:00"}
{"level":"info","msg":"Copied (new)","object":"testfile_01M_6","objectType":"*local.Object","size":1048576,"source":"operations/copy.go:360","time":"2024-05-04T02:12:38.584762+00:00"}
{"level":"info","msg":"Copied (new)","object":"testfile_01M_60","objectType":"*local.Object","size":1048576,"source":"operations/copy.go:360","time":"2024-05-04T02:12:38.885422+00:00"}
{"level":"info","msg":"Copied (new)","object":"testfile_01M_61","objectType":"*local.Object","size":1048576,"source":"operations/copy.go:360","time":"2024-05-04T02:12:38.918516+00:00"}
{"level":"info","msg":"Copied (new)","object":"testfile_01M_62","objectType":"*local.Object","size":1048576,"source":"operations/copy.go:360","time":"2024-05-04T02:12:39.319843+00:00"}
{"level":"info","msg":"Copied (new)","object":"testfile_01M_63","objectType":"*local.Object","size":1048576,"source":"operations/copy.go:360","time":"2024-05-04T02:12:39.322044+00:00"}
{"level":"info","msg":"Copied (new)","object":"testfile_01M_64","objectType":"*local.Object","size":1048576,"source":"operations/copy.go:360","time":"2024-05-04T02:12:39.642122+00:00"}
{"level":"info","msg":"Copied (new)","object":"testfile_01M_65","objectType":"*local.Object","size":1048576,"source":"operations/copy.go:360","time":"2024-05-04T02:12:39.687031+00:00"}
{"level":"info","msg":"Copied (new)","object":"testfile_01M_66","objectType":"*local.Object","size":1048576,"source":"operations/copy.go:360","time":"2024-05-04T02:12:40.056832+00:00"}
{"level":"info","msg":"Copied (new)","object":"testfile_01M_67","objectType":"*local.Object","size":1048576,"source":"operations/copy.go:360","time":"2024-05-04T02:12:40.058767+00:00"}
{"level":"info","msg":"Copied (new)","object":"testfile_01M_68","objectType":"*local.Object","size":1048576,"source":"operations/copy.go:360","time":"2024-05-04T02:12:40.39476+00:00"}
{"level":"info","msg":"Copied (new)","object":"testfile_01M_69","objectType":"*local.Object","size":1048576,"source":"operations/copy.go:360","time":"2024-05-04T02:12:40.449689+00:00"}
{"level":"info","msg":"Copied (new)","object":"testfile_01M_7","objectType":"*local.Object","size":1048576,"source":"operations/copy.go:360","time":"2024-05-04T02:12:40.78679+00:00"}
{"level":"info","msg":"Copied (new)","object":"testfile_01M_70","objectType":"*local.Object","size":1048576,"source":"operations/copy.go:360","time":"2024-05-04T02:12:40.802889+00:00"}
{"level":"info","msg":"Copied (new)","object":"testfile_01M_72","objectType":"*local.Object","size":1048576,"source":"operations/copy.go:360","time":"2024-05-04T02:12:41.211707+00:00"}
{"level":"info","msg":"Copied (new)","object":"testfile_01M_71","objectType":"*local.Object","size":1048576,"source":"operations/copy.go:360","time":"2024-05-04T02:12:41.376817+00:00"}
{"level":"info","msg":"Copied (new)","object":"testfile_01M_73","objectType":"*local.Object","size":1048576,"source":"operations/copy.go:360","time":"2024-05-04T02:12:41.516683+00:00"}
{"level":"info","msg":"Copied (new)","object":"testfile_01M_74","objectType":"*local.Object","size":1048576,"source":"operations/copy.go:360","time":"2024-05-04T02:12:41.53453+00:00"}
{"level":"info","msg":"Copied (new)","object":"testfile_01M_75","objectType":"*local.Object","size":1048576,"source":"operations/copy.go:360","time":"2024-05-04T02:12:41.973215+00:00"}
{"level":"info","msg":"Copied (new)","object":"testfile_01M_76","objectType":"*local.Object","size":1048576,"source":"operations/copy.go:360","time":"2024-05-04T02:12:42.132998+00:00"}
{"level":"info","msg":"Copied (new)","object":"testfile_01M_77","objectType":"*local.Object","size":1048576,"source":"operations/copy.go:360","time":"2024-05-04T02:12:42.245182+00:00"}
{"level":"info","msg":"Copied (new)","object":"testfile_01M_78","objectType":"*local.Object","size":1048576,"source":"operations/copy.go:360","time":"2024-05-04T02:12:42.262539+00:00"}
{"level":"info","msg":"Copied (new)","object":"testfile_01M_79","objectType":"*local.Object","size":1048576,"source":"operations/copy.go:360","time":"2024-05-04T02:12:42.733549+00:00"}
{"level":"info","msg":"Copied (new)","object":"testfile_01M_8","objectType":"*local.Object","size":1048576,"source":"operations/copy.go:360","time":"2024-05-04T02:12:42.884642+00:00"}
{"level":"info","msg":"Copied (new)","object":"testfile_01M_80","objectType":"*local.Object","size":1048576,"source":"operations/copy.go:360","time":"2024-05-04T02:12:42.97196+00:00"}
{"level":"info","msg":"Copied (new)","object":"testfile_01M_81","objectType":"*local.Object","size":1048576,"source":"operations/copy.go:360","time":"2024-05-04T02:12:42.990483+00:00"}
{"level":"info","msg":"Copied (new)","object":"testfile_01M_82","objectType":"*local.Object","size":1048576,"source":"operations/copy.go:360","time":"2024-05-04T02:12:43.493238+00:00"}
{"level":"info","msg":"Copied (new)","object":"testfile_01M_83","objectType":"*local.Object","size":1048576,"source":"operations/copy.go:360","time":"2024-05-04T02:12:43.633225+00:00"}
{"level":"info","msg":"Copied (new)","object":"testfile_01M_84","objectType":"*local.Object","size":1048576,"source":"operations/copy.go:360","time":"2024-05-04T02:12:43.697088+00:00"}
{"level":"info","msg":"Copied (new)","object":"testfile_01M_85","objectType":"*local.Object","size":1048576,"source":"operations/copy.go:360","time":"2024-05-04T02:12:43.715441+00:00"}
{"level":"info","msg":"Copied (new)","object":"testfile_01M_86","objectType":"*local.Object","size":1048576,"source":"operations/copy.go:360","time":"2024-05-04T02:12:44.255234+00:00"}
{"level":"info","msg":"Copied (new)","object":"testfile_01M_87","objectType":"*local.Object","size":1048576,"source":"operations/copy.go:360","time":"2024-05-04T02:12:44.383368+00:00"}
{"level":"info","msg":"Copied (new)","object":"testfile_01M_88","objectType":"*local.Object","size":1048576,"source":"operations/copy.go:360","time":"2024-05-04T02:12:44.423174+00:00"}
{"level":"info","msg":"Copied (new)","object":"testfile_01M_89","objectType":"*local.Object","size":1048576,"source":"operations/copy.go:360","time":"2024-05-04T02:12:44.443304+00:00"}
{"level":"info","msg":"Copied (new)","object":"testfile_01M_9","objectType":"*local.Object","size":1048576,"source":"operations/copy.go:360","time":"2024-05-04T02:12:45.015845+00:00"}
{"level":"info","msg":"Copied (new)","object":"testfile_01M_91","objectType":"*local.Object","size":1048576,"source":"operations/copy.go:360","time":"2024-05-04T02:12:45.229126+00:00"}
{"level":"info","msg":"Copied (new)","object":"testfile_01M_92","objectType":"*local.Object","size":1048576,"source":"operations/copy.go:360","time":"2024-05-04T02:12:45.231191+00:00"}
{"level":"info","msg":"Copied (new)","object":"testfile_01M_90","objectType":"*local.Object","size":1048576,"source":"operations/copy.go:360","time":"2024-05-04T02:12:45.254166+00:00"}
{"level":"info","msg":"Copied (new)","object":"testfile_01M_93","objectType":"*local.Object","size":1048576,"source":"operations/copy.go:360","time":"2024-05-04T02:12:45.773646+00:00"}
{"level":"info","msg":"Copied (new)","object":"testfile_01M_94","objectType":"*local.Object","size":1048576,"source":"operations/copy.go:360","time":"2024-05-04T02:12:45.971003+00:00"}
{"level":"info","msg":"Copied (new)","object":"testfile_01M_95","objectType":"*local.Object","size":1048576,"source":"operations/copy.go:360","time":"2024-05-04T02:12:45.977836+00:00"}
{"level":"info","msg":"Copied (new)","object":"testfile_01M_96","objectType":"*local.Object","size":1048576,"source":"operations/copy.go:360","time":"2024-05-04T02:12:46.007757+00:00"}
{"level":"info","msg":"Copied (new)","object":"testfile_01M_97","objectType":"*local.Object","size":1048576,"source":"operations/copy.go:360","time":"2024-05-04T02:12:46.531297+00:00"}
{"level":"info","msg":"Copied (new)","object":"testfile_01M_98","objectType":"*local.Object","size":1048576,"source":"operations/copy.go:360","time":"2024-05-04T02:12:46.694654+00:00"}
{"level":"info","msg":"Copied (new)","object":"testfile_01M_99","objectType":"*local.Object","size":1048576,"source":"operations/copy.go:360","time":"2024-05-04T02:12:46.70196+00:00"}
{"level":"info","msg":"\nTransferred:   \t      128 MiB / 128 MiB, 100%, 4.648 MiB/s, ETA 0s\nTransferred:          128 / 128, 100%\nElapsed time:        29.4s\n\n","source":"accounting/stats.go:526","stats":{"bytes":134217728,"checks":0,"deletedDirs":0,"deletes":0,"elapsedTime":29.411106902,"errors":0,"eta":0,"fatalError":false,"renames":0,"retryError":false,"serverSideCopies":0,"serverSideCopyBytes":0,"serverSideMoveBytes":0,"serverSideMoves":0,"speed":4873993.110671913,"totalBytes":134217728,"totalChecks":0,"totalTransfers":128,"transferTime":28.286037386,"transfers":128},"time":"2024-05-04T02:12:46.702185+00:00"}
